betterfilesystem/__init__.py
betterfilesystem/main.py
betterfilesystem-0.3.dist-info/METADATA
betterfilesystem-0.3.dist-info/WHEEL
betterfilesystem-0.3.dist-info/top_level.txt
betterfilesystem-0.3.dist-info/RECORD
