Metadata-Version: 2.1
Name: betterfilesystem
Version: 0.3
